synthDataGen/__init__.py
synthDataGen/adjustments.py
synthDataGen/controller.py
synthDataGen/utils.py
synthDataGen/common/__init__.py
synthDataGen/common/bibliotecaEsios.py
synthDataGen/common/bibliotecaGeneral.py
synthDataGen/settings/ficheroDeClaves.json
synthDataGen-0.4.dist-info/LICENSE
synthDataGen-0.4.dist-info/METADATA
synthDataGen-0.4.dist-info/WHEEL
synthDataGen-0.4.dist-info/top_level.txt
synthDataGen-0.4.dist-info/RECORD
