Metadata-Version: 2.1
Name: synthDataGen
Version: 0.4
Summary: An app based on pandas and scipy packages to load DataFrame-like tables either from remote or local repositories and generate synthetic samples from it.
Author-email: Santiago Fernández Prieto <mail.santiagofernandezprieto@gmail.com>, German Navarro <ge.najim@gmail.com>, David Aller Giraldez <d.aller.giraldez@gmail.com>
License: Apache License
Project-URL: Homepage, https://github.com/bsc-quantic/synthDataGen
Classifier: Programming Language :: Python :: 3
Classifier: Operating System :: OS Independent
Classifier: Topic :: System :: Archiving :: Mirroring
Requires-Python: >=3.10.7
License-File: LICENSE
Requires-Dist: pandas ==2.0.2
Requires-Dist: numpy ==1.23.3
Requires-Dist: scipy ==1.11.1
Requires-Dist: requests ==2.32.0
